a3cosmos/__init__.py
a3cosmos/__main__.py
a3cosmos/Data/20180801/A-COSMOS_Robust_Galaxy_Catalog_for_publishing.fits
a3cosmos/Data/20180801/A-COSMOS_Robust_Galaxy_Catalog_for_publishing.readme.txt
a3cosmos/Data/20180801/A-COSMOS_blind_2018-11-22_PyBDSF_with_meta_corrected_for_publishing.fits
a3cosmos/Data/20180801/A-COSMOS_blind_2018-11-22_PyBDSF_with_meta_corrected_for_publishing.readme.txt
a3cosmos/Data/20180801/A-COSMOS_prior_2018-12-29_Gaussian_with_meta_corrected_for_publishing.fits
a3cosmos/Data/20180801/A-COSMOS_prior_2018-12-29_Gaussian_with_meta_corrected_for_publishing.readme.txt
a3cosmos/Data/20180801/_ReadMe_A3COSMOS_Paper_1_Table_4_Photometry_Catalog_Description.pdf
a3cosmos/Data/20180801/_ReadMe_A3COSMOS_Paper_1_Table_5_Galaxy_Catalog_Description.pdf
a3cosmos/Data/20180801/a3cosmos_meta_table.fits
a3cosmos/Software/__init__.py
a3cosmos/Software/a3cosmos_cutouts_make_cutouts_for_input_images_by_RA_Dec.py
a3cosmos/Software/a3cosmos_cutouts_query_cosmos_cutouts_via_IRSA_HTTP_URL.py
a3cosmos/Software/module_find_source.py
a3cosmos/Software/module_make_cutout.py
a3cosmos-0.9.3.dist-info/AUTHORS.txt
a3cosmos-0.9.3.dist-info/LICENSE.txt
a3cosmos-0.9.3.dist-info/METADATA
a3cosmos-0.9.3.dist-info/WHEEL
a3cosmos-0.9.3.dist-info/top_level.txt
a3cosmos-0.9.3.dist-info/RECORD
